Metadata-Version: 1.0
Name: blitz-hash
Version: 0.1
Summary: SIMD and coprocessor accelerated hashing functions
Home-page: http://blitz.works/blitz-hash
Author: Da_Blitz
Author-email: code@blitz.works
License: MIT BSD
Keywords: sha sha1 sha256 hashlib hash turbo neon intrinsics simd sse
Platform: UNKNOWN
